[{"text":"aplausos","value":6.0},{"text":"a\u00f1o","value":3.4468073223},{"text":"a\u00f1os","value":8.7452930037},{"text":"base","value":3.6487102583},{"text":"bolivia","value":5.576652903},{"text":"datos","value":3.4591011771},{"text":"debate","value":3.4297327003},{"text":"debates","value":3.4914088427},{"text":"democracia","value":4.4463793417},{"text":"econom\u00eda","value":6.4255963846},{"text":"electoral","value":4.7153530823},{"text":"empresas","value":4.5788721462},{"text":"encuesta","value":4.4497121066},{"text":"encuestas","value":11.4030841754},{"text":"evo","value":6.1425238721},{"text":"fraude","value":5.8326347438},{"text":"gente","value":10.7832767229},{"text":"manipulaci\u00f3n","value":5.7840627854},{"text":"manipular","value":3.8021911665},{"text":"mil","value":3.7751575974},{"text":"miles","value":4.4558685457},{"text":"morales","value":5.9304264004},{"text":"mostrar","value":4.138861551},{"text":"muestra","value":4.1007288905},{"text":"pa\u00eds","value":5.1700314184},{"text":"presidente","value":5.1382552302},{"text":"resultado","value":4.1717821885},{"text":"se\u00f1or","value":3.7374636419},{"text":"sistema","value":5.0216015263},{"text":"votar","value":4.5967536611}]